{
    "key": "group_layouts",
    "title": "Post layouts",
    "fields": [
        {
            "key": "field_5dae91109c770",
            "label": "Layouts",
            "name": "layouts",
            "type": "flexible_content",
            "instructions": "",
            "required": 0,
            "conditional_logic": 0,
            "wrapper": {
                "width": "",
                "class": "",
                "id": ""
            },
            "layouts": {
                "layout_5ff7f0e90fee9": {
                    "key": "layout_5ff7f0e90fee9",
                    "name": "article",
                    "label": "Article",
                    "display": "block",
                    "sub_fields": [
                        {
                            "key": "field_5ff7f0f00feea",
                            "label": "",
                            "name": "",
                            "type": "clone",
                            "instructions": "",
                            "required": 0,
                            "conditional_logic": 0,
                            "wrapper": {
                                "width": "",
                                "class": "",
                                "id": ""
                            },
                            "clone": [
                                "group_5ff7ef630d945"
                            ],
                            "display": "seamless",
                            "layout": "block",
                            "prefix_label": 0,
                            "prefix_name": 0
                        }
                    ],
                    "min": "",
                    "max": ""
                },
                "layout_61f3c30bc11cd": {
                    "key": "layout_61f3c30bc11cd",
                    "name": "topnav",
                    "label": "TopNav",
                    "display": "block",
                    "sub_fields": [
                        {
                            "key": "field_61f3c31cc11ce",
                            "label": "",
                            "name": "",
                            "type": "clone",
                            "instructions": "",
                            "required": 0,
                            "conditional_logic": 0,
                            "wrapper": {
                                "width": "",
                                "class": "",
                                "id": ""
                            },
                            "clone": [
                                "group_61f3bf1ecfda6"
                            ],
                            "display": "seamless",
                            "layout": "block",
                            "prefix_label": 0,
                            "prefix_name": 0
                        }
                    ],
                    "min": "",
                    "max": ""
                },
                "layout_62b321bdcf25c": {
                    "key": "layout_62b321bdcf25c",
                    "name": "linkcard",
                    "label": "LinkCard",
                    "display": "block",
                    "sub_fields": [
                        {
                            "key": "field_62b321cccf25d",
                            "label": "",
                            "name": "",
                            "type": "clone",
                            "instructions": "",
                            "required": 0,
                            "conditional_logic": 0,
                            "wrapper": {
                                "width": "",
                                "class": "",
                                "id": ""
                            },
                            "clone": [
                                "group_62b3210f9df0a"
                            ],
                            "display": "seamless",
                            "layout": "block",
                            "prefix_label": 0,
                            "prefix_name": 0
                        }
                    ],
                    "min": "",
                    "max": ""
                },
                "layout_61f3e0498f395": {
                    "key": "layout_61f3e0498f395",
                    "name": "heromedia",
                    "label": "HeroMedia",
                    "display": "block",
                    "sub_fields": [
                        {
                            "key": "field_61f3e0598f396",
                            "label": "",
                            "name": "",
                            "type": "clone",
                            "instructions": "",
                            "required": 0,
                            "conditional_logic": 0,
                            "wrapper": {
                                "width": "",
                                "class": "",
                                "id": ""
                            },
                            "clone": [
                                "group_61f3df59a6eb7"
                            ],
                            "display": "seamless",
                            "layout": "block",
                            "prefix_label": 0,
                            "prefix_name": 0
                        }
                    ],
                    "min": "",
                    "max": ""
                },
                "layout_61fe71b1f70c4": {
                    "key": "layout_61fe71b1f70c4",
                    "name": "heroresultdisplay",
                    "label": "HeroResultDisplay",
                    "display": "block",
                    "sub_fields": [
                        {
                            "key": "field_61fe73905c549",
                            "label": "",
                            "name": "",
                            "type": "clone",
                            "instructions": "",
                            "required": 0,
                            "conditional_logic": 0,
                            "wrapper": {
                                "width": "",
                                "class": "",
                                "id": ""
                            },
                            "clone": [
                                "group_61fe6efbdedf0"
                            ],
                            "display": "seamless",
                            "layout": "block",
                            "prefix_label": 0,
                            "prefix_name": 0
                        }
                    ],
                    "min": "",
                    "max": ""
                },
                "layout_61f79a236bd0f": {
                    "key": "layout_61f79a236bd0f",
                    "name": "foxgallary",
                    "label": "FoxGallary",
                    "display": "block",
                    "sub_fields": [
                        {
                            "key": "field_61f79a396bd10",
                            "label": "",
                            "name": "",
                            "type": "clone",
                            "instructions": "",
                            "required": 0,
                            "conditional_logic": 0,
                            "wrapper": {
                                "width": "",
                                "class": "",
                                "id": ""
                            },
                            "clone": [
                                "group_61f79986e1cae"
                            ],
                            "display": "seamless",
                            "layout": "block",
                            "prefix_label": 0,
                            "prefix_name": 0
                        }
                    ],
                    "min": "",
                    "max": ""
                },
                "layout_61f7c2409e52b": {
                    "key": "layout_61f7c2409e52b",
                    "name": "bookdisplay",
                    "label": "BookDisplay",
                    "display": "block",
                    "sub_fields": [
                        {
                            "key": "field_61f7c24d9e52c",
                            "label": "",
                            "name": "",
                            "type": "clone",
                            "instructions": "",
                            "required": 0,
                            "conditional_logic": 0,
                            "wrapper": {
                                "width": "",
                                "class": "",
                                "id": ""
                            },
                            "clone": [
                                "group_61f7c1a1b2519"
                            ],
                            "display": "seamless",
                            "layout": "block",
                            "prefix_label": 0,
                            "prefix_name": 0
                        }
                    ],
                    "min": "",
                    "max": ""
                },
                "layout_61f3ffa0ac04b": {
                    "key": "layout_61f3ffa0ac04b",
                    "name": "imagedisplay",
                    "label": "ImageDisplay",
                    "display": "block",
                    "sub_fields": [
                        {
                            "key": "field_61f3ffadac04c",
                            "label": "",
                            "name": "",
                            "type": "clone",
                            "instructions": "",
                            "required": 0,
                            "conditional_logic": 0,
                            "wrapper": {
                                "width": "",
                                "class": "",
                                "id": ""
                            },
                            "clone": [
                                "group_61f3ff273512a"
                            ],
                            "display": "seamless",
                            "layout": "block",
                            "prefix_label": 0,
                            "prefix_name": 0
                        }
                    ],
                    "min": "",
                    "max": ""
                },
                "layout_61fa84c45e809": {
                    "key": "layout_61fa84c45e809",
                    "name": "heromediaquiz",
                    "label": "HeroMediaQuiz",
                    "display": "block",
                    "sub_fields": [
                        {
                            "key": "field_61fa84d45e80a",
                            "label": "",
                            "name": "",
                            "type": "clone",
                            "instructions": "",
                            "required": 0,
                            "conditional_logic": 0,
                            "wrapper": {
                                "width": "",
                                "class": "",
                                "id": ""
                            },
                            "clone": [
                                "group_61fa81cac1be8"
                            ],
                            "display": "seamless",
                            "layout": "block",
                            "prefix_label": 0,
                            "prefix_name": 0
                        }
                    ],
                    "min": "",
                    "max": ""
                },
                "layout_5e5f5f69a45c0": {
                    "key": "layout_5e5f5f69a45c0",
                    "name": "hero",
                    "label": "Hero",
                    "display": "block",
                    "sub_fields": [
                        {
                            "key": "field_5e5f5f76a45c1",
                            "label": "",
                            "name": "",
                            "type": "clone",
                            "instructions": "",
                            "required": 0,
                            "conditional_logic": 0,
                            "wrapper": {
                                "width": "",
                                "class": "",
                                "id": ""
                            },
                            "clone": [
                                "group_5e5f55df65785"
                            ],
                            "display": "seamless",
                            "layout": "block",
                            "prefix_label": 0,
                            "prefix_name": 0
                        }
                    ],
                    "min": "",
                    "max": ""
                },
                "layout_5ff7f72348d6a": {
                    "key": "layout_5ff7f72348d6a",
                    "name": "icon_linklist",
                    "label": "IconLinklist",
                    "display": "block",
                    "sub_fields": [
                        {
                            "key": "field_5ff7f72348d6b",
                            "label": "",
                            "name": "",
                            "type": "clone",
                            "instructions": "",
                            "required": 0,
                            "conditional_logic": 0,
                            "wrapper": {
                                "width": "",
                                "class": "",
                                "id": ""
                            },
                            "clone": [
                                "group_5ff7f6b6717bd"
                            ],
                            "display": "seamless",
                            "layout": "block",
                            "prefix_label": 0,
                            "prefix_name": 0
                        }
                    ],
                    "min": "",
                    "max": ""
                },
                "layout_5fd32dac14975": {
                    "key": "layout_5fd32dac14975",
                    "name": "linklist",
                    "label": "Linklist",
                    "display": "block",
                    "sub_fields": [
                        {
                            "key": "field_5fd32db514976",
                            "label": "",
                            "name": "",
                            "type": "clone",
                            "instructions": "",
                            "required": 0,
                            "conditional_logic": 0,
                            "wrapper": {
                                "width": "",
                                "class": "",
                                "id": ""
                            },
                            "clone": [
                                "group_5fd7362b6d646"
                            ],
                            "display": "seamless",
                            "layout": "",
                            "prefix_label": 0,
                            "prefix_name": 0
                        }
                    ],
                    "min": "",
                    "max": ""
                },
                "layout_5ff8268a3e7bc": {
                    "key": "layout_5ff8268a3e7bc",
                    "name": "map",
                    "label": "Map",
                    "display": "block",
                    "sub_fields": [
                        {
                            "key": "field_5ff826913e7bd",
                            "label": "",
                            "name": "",
                            "type": "clone",
                            "instructions": "",
                            "required": 0,
                            "conditional_logic": 0,
                            "wrapper": {
                                "width": "",
                                "class": "",
                                "id": ""
                            },
                            "clone": [
                                "group_5ff8261db9890"
                            ],
                            "display": "seamless",
                            "layout": "block",
                            "prefix_label": 0,
                            "prefix_name": 0
                        }
                    ],
                    "min": "",
                    "max": ""
                },
                "layout_5ff843523a0e9": {
                    "key": "layout_5ff843523a0e9",
                    "name": "some_navigation",
                    "label": "Some navigation",
                    "display": "block",
                    "sub_fields": [
                        {
                            "key": "field_5ff8435e3a0ea",
                            "label": "",
                            "name": "",
                            "type": "clone",
                            "instructions": "",
                            "required": 0,
                            "conditional_logic": 0,
                            "wrapper": {
                                "width": "",
                                "class": "",
                                "id": ""
                            },
                            "clone": [
                                "group_5ff842d80c812"
                            ],
                            "display": "seamless",
                            "layout": "block",
                            "prefix_label": 0,
                            "prefix_name": 0
                        }
                    ],
                    "min": "",
                    "max": ""
                },
                "layout_5ff83820dbe95": {
                    "key": "layout_5ff83820dbe95",
                    "name": "timeline",
                    "label": "Timeline",
                    "display": "block",
                    "sub_fields": [
                        {
                            "key": "field_5ff8382adbe96",
                            "label": "",
                            "name": "",
                            "type": "clone",
                            "instructions": "",
                            "required": 0,
                            "conditional_logic": 0,
                            "wrapper": {
                                "width": "",
                                "class": "",
                                "id": ""
                            },
                            "clone": [
                                "group_5ff837dfc8b2e"
                            ],
                            "display": "seamless",
                            "layout": "block",
                            "prefix_label": 0,
                            "prefix_name": 0
                        }
                    ],
                    "min": "",
                    "max": ""
                },
                "layout_6040e2dc594fa": {
                    "key": "layout_6040e2dc594fa",
                    "name": "timeline_textual",
                    "label": "Timeline textual",
                    "display": "block",
                    "sub_fields": [
                        {
                            "key": "field_6040e2ed594fb",
                            "label": "",
                            "name": "",
                            "type": "clone",
                            "instructions": "",
                            "required": 0,
                            "conditional_logic": 0,
                            "wrapper": {
                                "width": "",
                                "class": "",
                                "id": ""
                            },
                            "clone": [
                                "group_6040e1de867b9"
                            ],
                            "display": "seamless",
                            "layout": "block",
                            "prefix_label": 0,
                            "prefix_name": 0
                        }
                    ],
                    "min": "",
                    "max": ""
                }
            },
            "button_label": "Add Row",
            "min": "",
            "max": ""
        }
    ],
    "location": [
        [
            {
                "param": "post_type",
                "operator": "==",
                "value": "page"
            }
        ],
        [
            {
                "param": "post_type",
                "operator": "==",
                "value": "post"
            }
        ]
    ],
    "menu_order": 0,
    "position": "normal",
    "style": "default",
    "label_placement": "top",
    "instruction_placement": "label",
    "hide_on_screen": "",
    "active": true,
    "description": "layout_modules",
    "show_in_rest": 0,
    "modified": 1655906823
}